fds/__init__.py
fds/sdk/__init__.py
fds/sdk/NewsAPIforDigitalPortals/__init__.py
fds/sdk/NewsAPIforDigitalPortals/api_client.py
fds/sdk/NewsAPIforDigitalPortals/configuration.py
fds/sdk/NewsAPIforDigitalPortals/exceptions.py
fds/sdk/NewsAPIforDigitalPortals/model_utils.py
fds/sdk/NewsAPIforDigitalPortals/rest.py
fds/sdk/NewsAPIforDigitalPortals/api/__init__.py
fds/sdk/NewsAPIforDigitalPortals/api/news_api.py
fds/sdk/NewsAPIforDigitalPortals/apis/__init__.py
fds/sdk/NewsAPIforDigitalPortals/model/__init__.py
fds/sdk/NewsAPIforDigitalPortals/model/attributes_member.py
fds/sdk/NewsAPIforDigitalPortals/model/cursor_based_pagination_output_object.py
fds/sdk/NewsAPIforDigitalPortals/model/cursor_based_pagination_output_object_without_total.py
fds/sdk/NewsAPIforDigitalPortals/model/error_meta_object.py
fds/sdk/NewsAPIforDigitalPortals/model/error_object.py
fds/sdk/NewsAPIforDigitalPortals/model/inline_response200.py
fds/sdk/NewsAPIforDigitalPortals/model/inline_response2001.py
fds/sdk/NewsAPIforDigitalPortals/model/inline_response20010.py
fds/sdk/NewsAPIforDigitalPortals/model/inline_response20010_data.py
fds/sdk/NewsAPIforDigitalPortals/model/inline_response20010_meta.py
fds/sdk/NewsAPIforDigitalPortals/model/inline_response20011.py
fds/sdk/NewsAPIforDigitalPortals/model/inline_response20011_data.py
fds/sdk/NewsAPIforDigitalPortals/model/inline_response2001_categories.py
fds/sdk/NewsAPIforDigitalPortals/model/inline_response2001_chain.py
fds/sdk/NewsAPIforDigitalPortals/model/inline_response2001_data.py
fds/sdk/NewsAPIforDigitalPortals/model/inline_response2001_distributor.py
fds/sdk/NewsAPIforDigitalPortals/model/inline_response2001_fsym.py
fds/sdk/NewsAPIforDigitalPortals/model/inline_response2001_fsym_security.py
fds/sdk/NewsAPIforDigitalPortals/model/inline_response2001_instruments.py
fds/sdk/NewsAPIforDigitalPortals/model/inline_response2001_language.py
fds/sdk/NewsAPIforDigitalPortals/model/inline_response2001_meta.py
fds.sdk.NewsAPIforDigitalPortals-0.10.10.dist-info/LICENSE
fds.sdk.NewsAPIforDigitalPortals-0.10.10.dist-info/METADATA
fds.sdk.NewsAPIforDigitalPortals-0.10.10.dist-info/WHEEL
fds.sdk.NewsAPIforDigitalPortals-0.10.10.dist-info/top_level.txt
fds.sdk.NewsAPIforDigitalPortals-0.10.10.dist-info/RECORD
